MANIFEST.in
README.txt
setup.cfg
setup.py
docs/HISTORY.txt
docs/TODO.txt
pydataportability/__init__.py
pydataportability.model.resource.egg-info/PKG-INFO
pydataportability.model.resource.egg-info/SOURCES.txt
pydataportability.model.resource.egg-info/dependency_links.txt
pydataportability.model.resource.egg-info/entry_points.txt
pydataportability.model.resource.egg-info/namespace_packages.txt
pydataportability.model.resource.egg-info/not-zip-safe
pydataportability.model.resource.egg-info/requires.txt
pydataportability.model.resource.egg-info/top_level.txt
pydataportability/model/__init__.py
pydataportability/model/resource/__init__.py
pydataportability/model/resource/interfaces.py
pydataportability/model/resource/models.py
pydataportability/model/resource/tests/__init__.py
pydataportability/model/resource/tests/conftest.py
pydataportability/model/resource/tests/test_resourceset.py
pydataportability/model/resource/tests/test_uritemplates.py