Metadata-Version: 1.0
Name: pydataportability.model.resource
Version: 0.4
Summary: Model classes and interfaces for resource descriptions for pydataportability and e.g. XRD parsers
Home-page: http://pydataportability.net
Author: Christian Scholz
Author-email: cs@comlounge.net
License: BSD
Keywords: dataportability openweb diso xrd resources models
Platform: UNKNOWN
Classifier: Programming Language :: Python
Classifier: Topic :: Software Development :: Libraries :: Python Modules
